Workbook

Sheet Comparação
A1: SKU | B1: Nosso produto | C1: No site? | D1: Preço OMG hoje (R$) | E1: Situação | F1: Produto oficial | G1: Variante | H1: Preço oficial (US$) | I1: Preço cheio (US$) | J1: Disponível lá? | K1: Link oficial | L1: Mercadoria sugerida (R$) | M1: Diferença vs hoje | N1: Observação
A2: MB003075 | B2: 1025 Bálsamo de Limpeza Dokdo 50ml | C2: Sim | D2: 174.9 | E2: Certeiro | F2: 1025 Dokdo Cleansing Balm 50ml | G2: 50ml | H2: 22.4 | I2: 28 | J2: Sim | K2: https://roundlab.com/products/1025-dokdo-cleansing-balm-50ml | L2: =ROUND(H2*(1+Parâmetros!$B$2)*Parâmetros!$B$1,2) | M2: =IF(OR(D2="",L2=""),"",D2/L2-1)
A3: MB000634 | B3: 1025 Dokdo Ampoule: ampola hidratante com ácido hialurônico 45 g | C3: Sim | D3: 225.9 | E3: Certeiro | F3: 1025 Dokdo Ampoule | H3: 24.8 | I3: 31 | J3: Sim | K3: https://roundlab.com/products/1025-dokdo-ampoule | L3: =ROUND(H3*(1+Parâmetros!$B$2)*Parâmetros!$B$1,2) | M3: =IF(OR(D3="",L3=""),"",D3/L3-1)
A4: MB000618 | B4: 1025 Dokdo Cleanser: espuma de limpeza suave de pH baixo 150 ml | C4: Sim | D4: 123.9 | E4: Certeiro | F4: 1025 Dokdo Cleanser | H4: 13.6 | I4: 17 | J4: Sim | K4: https://roundlab.com/products/1025-dokdo-cleanser | L4: =ROUND(H4*(1+Parâmetros!$B$2)*Parâmetros!$B$1,2) | M4: =IF(OR(D4="",L4=""),"",D4/L4-1)
A5: MB000632 | B5: 1025 Dokdo Cleansing Balm: bálsamo demaquilante em bastão 50 ml | C5: Sim | D5: 174.9 | E5: Certeiro | F5: 1025 Dokdo Cleansing Balm 50ml | G5: 50ml | H5: 22.4 | I5: 28 | J5: Sim | K5: https://roundlab.com/products/1025-dokdo-cleansing-balm-50ml | L5: =ROUND(H5*(1+Parâmetros!$B$2)*Parâmetros!$B$1,2) | M5: =IF(OR(D5="",L5=""),"",D5/L5-1)
A6: MB000631 | B6: 1025 Dokdo Cleansing Gel: gel de limpeza de pH baixo com ácido hialurônico 150 ml | C6: Sim | D6: 188.9 | E6: Certeiro | F6: 1025 Dokdo Cleansing Gel | H6: 20.8 | I6: 26 | J6: Sim | K6: https://roundlab.com/products/1025-dokdo-cleansing-gel | L6: =ROUND(H6*(1+Parâmetros!$B$2)*Parâmetros!$B$1,2) | M6: =IF(OR(D6="",L6=""),"",D6/L6-1)
A7: MB000630 | B7: 1025 Dokdo Cleansing Oil: óleo de limpeza leve com água do mar profundo 200 ml | C7: Sim | D7: 98.9 | E7: Certeiro | F7: 1025 Dokdo Cleansing Oil | H7: 20.8 | I7: 26 | J7: Sim | K7: https://roundlab.com/products/1025-dokdo-cleansing-oil | L7: =ROUND(H7*(1+Parâmetros!$B$2)*Parâmetros!$B$1,2) | M7: =IF(OR(D7="",L7=""),"",D7/L7-1)
A8: MB000629 | B8: 1025 Dokdo Cream: creme hidratante com 5 ceramidas 80 ml | C8: Sim | D8: 261.9 | E8: Certeiro | F8: 1025 Dokdo Cream | H8: 28.8 | I8: 36 | J8: Sim | K8: https://roundlab.com/products/1025-dokdo-cream | L8: =ROUND(H8*(1+Parâmetros!$B$2)*Parâmetros!$B$1,2) | M8: =IF(OR(D8="",L8=""),"",D8/L8-1)
A9: MB000628 | B9: 1025 Dokdo Lotion: hidratante leve com água do mar profundo 200 ml | C9: Sim | D9: 159.9 | E9: Certeiro | F9: 1025 Dokdo Lotion | H9: 17.6 | I9: 22 | J9: Sim | K9: https://roundlab.com/products/1025-dokdo-lotion | L9: =ROUND(H9*(1+Parâmetros!$B$2)*Parâmetros!$B$1,2) | M9: =IF(OR(D9="",L9=""),"",D9/L9-1)
A10: MB003109 | B10: 1025 Dokdo Lotion: loção hidratante 400 ml | C10: Sim | D10: 214.9 | E10: Certeiro | F10: 1025 Dokdo Lotion | H10: 17.6 | I10: 22 | J10: Sim | K10: https://roundlab.com/products/1025-dokdo-lotion | L10: =ROUND(H10*(1+Parâmetros!$B$2)*Parâmetros!$B$1,2) | M10: =IF(OR(D10="",L10=""),"",D10/L10-1)
A11: MB000627 | B11: 1025 Dokdo Mud Pack: máscara de argila para poros 100 ml | C11: Sim | D11: 137.9 | E11: Certeiro | F11: 1025 Dokdo Mud Pack | H11: 15.2 | I11: 19 | J11: Sim | K11: https://roundlab.com/products/1025-dokdo-mud-pack | L11: =ROUND(H11*(1+Parâmetros!$B$2)*Parâmetros!$B$1,2) | M11: =IF(OR(D11="",L11=""),"",D11/L11-1)
A12: MB000626 | B12: 1025 Dokdo Peeling Gel: gel esfoliante gommage com ácido hialurônico 120 ml | C12: Sim | D12: 174.9 | E12: Certeiro | F12: 1025 Dokdo Peeling Gel | H12: 19.2 | I12: 24 | J12: Sim | K12: https://roundlab.com/products/1025-dokdo-peeling-gel | L12: =ROUND(H12*(1+Parâmetros!$B$2)*Parâmetros!$B$1,2) | M12: =IF(OR(D12="",L12=""),"",D12/L12-1)
A13: MB000625 | B13: 1025 Dokdo Sleeping Pack: máscara noturna hidratante com PHA 100 ml | C13: Sim | D13: 174.9 | E13: Certeiro | F13: 1025 Dokdo Sleeping Pack | H13: 19.2 | I13: 24 | J13: Sim | K13: https://roundlab.com/products/1025-dokdo-sleeping-pack | L13: =ROUND(H13*(1+Parâmetros!$B$2)*Parâmetros!$B$1,2) | M13: =IF(OR(D13="",L13=""),"",D13/L13-1)
A14: MB000622 | B14: 1025 Dokdo Toner Pad: discos de tônico com água do mar profundo, 70 unidades | C14: Sim | D14: 195.9 | E14: Certeiro | F14: 1025 Dokdo Toner Pad | H14: 21.6 | I14: 27 | J14: Sim | K14: https://roundlab.com/products/1025-dokdo-pad | L14: =ROUND(H14*(1+Parâmetros!$B$2)*Parâmetros!$B$1,2) | M14: =IF(OR(D14="",L14=""),"",D14/L14-1)
A15: MB003094 | B15: 1025 Dokdo Toner: tônico 200 ml | C15: Sim | D15: 146.9 | E15: Certeiro | F15: 1025 Dokdo Toner | G15: 200ml | H15: 13.6 | I15: 17 | J15: Sim | K15: https://roundlab.com/products/1025-dokdo-toner?variant=43023567749334 | L15: =ROUND(H15*(1+Parâmetros!$B$2)*Parâmetros!$B$1,2) | M15: =IF(OR(D15="",L15=""),"",D15/L15-1)
A16: MB003117 | B16: 1025 Dokdo Toner: tônico em tamanho grande 500 ml | C16: Sim | D16: 247.9 | E16: Certeiro | F16: 1025 Dokdo Toner | G16: 500ml | H16: 27.2 | I16: 34 | J16: Sim | K16: https://roundlab.com/products/1025-dokdo-toner?variant=43023567782102 | L16: =ROUND(H16*(1+Parâmetros!$B$2)*Parâmetros!$B$1,2) | M16: =IF(OR(D16="",L16=""),"",D16/L16-1)
A17: MB000615 | B17: 1025 Dokdo Water Gel Mask: máscara em folha de gel hidratante (brinde) | C17: Sim | D17: 31.9 | E17: Certeiro | F17: 1025 Dokdo Water Gel Mask Sheet | G17: 1 PC | H17: 3.2 | I17: 4 | J17: Sim | K17: https://roundlab.com/products/1025-dokdo-mask-sheet?variant=44067260465366 | L17: =ROUND(H17*(1+Parâmetros!$B$2)*Parâmetros!$B$1,2) | M17: =IF(OR(D17="",L17=""),"",D17/L17-1)
A18: MB000619 | B18: 1025 Dokdo Water Gel Mask: máscara em folha de gel hidratante 30 ml | C18: Sim | D18: 28.9 | E18: Certeiro | F18: 1025 Dokdo Water Gel Mask Sheet | G18: 1 PC | H18: 3.2 | I18: 4 | J18: Sim | K18: https://roundlab.com/products/1025-dokdo-mask-sheet?variant=44067260465366 | L18: =ROUND(H18*(1+Parâmetros!$B$2)*Parâmetros!$B$1,2) | M18: =IF(OR(D18="",L18=""),"",D18/L18-1)
A19: MB003086 | B19: 1025 Dokdo: sabonete líquido 200 ml | C19: Sim | D19: 90.9 | E19: Certeiro | F19: 1025 Dokdo Toner | G19: 200ml | H19: 13.6 | I19: 17 | J19: Sim | K19: https://roundlab.com/products/1025-dokdo-toner?variant=43023567749334 | L19: =ROUND(H19*(1+Parâmetros!$B$2)*Parâmetros!$B$1,2) | M19: =IF(OR(D19="",L19=""),"",D19/L19-1)
A20: MB000608 | B20: Birch Juice Cleansing Pad: discos demaquilantes de seiva de bétula, 60 unidades | C20: Sim | D20: 174.9 | E20: Certeiro | F20: Birch Juice Cleansing Pad | H20: 24 | J20: Sim | K20: https://roundlab.com/products/birch-juice-cleansing-pad | L20: =ROUND(H20*(1+Parâmetros!$B$2)*Parâmetros!$B$1,2) | M20: =IF(OR(D20="",L20=""),"",D20/L20-1)
A21: MB000607 | B21: Birch Juice Moisturizing Ampoule: ampola hidratante com 10 ácidos hialurônicos 50 ml | C21: Sim | D21: 191.9 | E21: Certeiro | F21: Birch Juice Moisturizing Ampoule | H21: 26.35 | I21: 31 | J21: Sim | K21: https://roundlab.com/products/birch-juice-ampoule | L21: =ROUND(H21*(1+Parâmetros!$B$2)*Parâmetros!$B$1,2) | M21: =IF(OR(D21="",L21=""),"",D21/L21-1)
A22: MB000606 | B22: Birch Juice Moisturizing Peeling Cleansing Oil: óleo de limpeza com bétula 200 ml | C22: Sim | D22: 181.9 | E22: Certeiro | F22: Birch Juice Moisturizing Peeling Cleansing Oil | H22: 25 | J22: Sim | K22: https://roundlab.com/products/birch-juice-moisturizing-peeling-cleansing-oil | L22: =ROUND(H22*(1+Parâmetros!$B$2)*Parâmetros!$B$1,2) | M22: =IF(OR(D22="",L22=""),"",D22/L22-1)
A23: MB000605 | B23: Birch Juice Moisturizing Sun Serum: sérum protetor solar FPS 50 50 ml | C23: Sim | D23: 181.9 | E23: Certeiro | F23: Birch Juice Moisturizing Sun Serum SPF 50 | H23: 24.99 | J23: Sim | K23: https://roundlab.com/products/birch-juice-moisturizing-sun-serum-spf50 | L23: =ROUND(H23*(1+Parâmetros!$B$2)*Parâmetros!$B$1,2) | M23: =IF(OR(D23="",L23=""),"",D23/L23-1)
A24: MB000603 | B24: Birch Moisturizing Cleanser: gel de limpeza hidratante de pH baixo 150 ml | C24: Sim | D24: 104.9 | E24: Certeiro | F24: Birch Moisturizing Cleanser | H24: 14.45 | I24: 17 | J24: Sim | K24: https://roundlab.com/products/birch-moisturizing-cleanser | L24: =ROUND(H24*(1+Parâmetros!$B$2)*Parâmetros!$B$1,2) | M24: =IF(OR(D24="",L24=""),"",D24/L24-1)
A25: MB000600 | B25: Birch Moisturizing Double Gel Mask: máscara de hidrogel hidratante de bétula | C25: Sim | D25: 23.9 | E25: Certeiro | F25: Birch Moisturizing Double Gel Mask | G25: 10 pc | H25: 30.6 | I25: 36 | J25: Sim | K25: https://roundlab.com/products/birch-moisturizing-gel-mask?variant=47156793639126 | L25: =ROUND(H25*(1+Parâmetros!$B$2)*Parâmetros!$B$1,2) | M25: =IF(OR(D25="",L25=""),"",D25/L25-1)
A26: MB000599 | B26: Birch Moisturizing Eye Balm: bálsamo hidratante para a área dos olhos com bétula 10 g | C26: Sim | D26: 159.9 | E26: Certeiro | F26: Birch Moisturizing Eye Balm | H26: 22 | J26: Sim | K26: https://roundlab.com/products/round-lab-birch-juice-moisturizing-eye-balm-10g | L26: =ROUND(H26*(1+Parâmetros!$B$2)*Parâmetros!$B$1,2) | M26: =IF(OR(D26="",L26=""),"",D26/L26-1)
A27: MB000598 | B27: Birch Moisturizing Hand Cream: creme hidratante para as mãos com bétula 30 ml | C27: Sim | D27: 61.9 | E27: Certeiro | F27: Birch Moisturizing Hand Cream | H27: 8.5 | J27: Sim | K27: https://roundlab.com/products/birch-moisturizing-hand-cream | L27: =ROUND(H27*(1+Parâmetros!$B$2)*Parâmetros!$B$1,2) | M27: =IF(OR(D27="",L27=""),"",D27/L27-1)
A28: MB000597 | B28: Birch Moisturizing Intensive Cream: creme hidratante intensivo com bétula e ectoína | C28: Sim | D28: 290.9 | E28: Certeiro | F28: Birch Moisturizing Intensive Cream | H28: 40 | J28: Sim | K28: https://roundlab.com/products/birch-moisturizing-intensive-cream | L28: =ROUND(H28*(1+Parâmetros!$B$2)*Parâmetros!$B$1,2) | M28: =IF(OR(D28="",L28=""),"",D28/L28-1)
A29: MB000596 | B29: Birch Moisturizing Lip Balm: bálsamo labial hidratante com bétula 20 g | C29: Sim | D29: 135.9 | E29: Certeiro | F29: Birch Moisturizing Lip Balm | H29: 18.7 | I29: 22 | J29: Esgotado | K29: https://roundlab.com/products/birch-moisturizing-lip-balm | L29: =ROUND(H29*(1+Parâmetros!$B$2)*Parâmetros!$B$1,2) | M29: =IF(OR(D29="",L29=""),"",D29/L29-1)
A30: MB000594 | B30: Birch Moisturizing Sheet Mask: máscara em folha hidratante de bétula 25 ml | C30: Sim | D30: 23.9 | E30: Certeiro | F30: Birch Moisturizing Sheet Mask | G30: 1 PC | H30: 3.4 | I30: 4 | J30: Sim | K30: https://roundlab.com/products/birch-moisturizing-sheet-mask?variant=43610237173974 | L30: =ROUND(H30*(1+Parâmetros!$B$2)*Parâmetros!$B$1,2) | M30: =IF(OR(D30="",L30=""),"",D30/L30-1)
A31: MB000593 | B31: Birch Moisturizing Soothing Gel: gel calmante hidratante de bétula 150 ml | C31: Sim | D31: 101.9 | E31: Certeiro | F31: Birch Moisturizing Soothing Gel | H31: 14 | J31: Sim | K31: https://roundlab.com/products/birch-moisturizing-soothing-gel | L31: =ROUND(H31*(1+Parâmetros!$B$2)*Parâmetros!$B$1,2) | M31: =IF(OR(D31="",L31=""),"",D31/L31-1)
A32: MB000592 | B32: Birch Moisturizing Sun Cushion: protetor solar mineral em cushion FPS 50 15 g | C32: Sim | D32: 166.9 | E32: Certeiro | F32: Birch Moisturizing Sun Cushion SPF 50 | H32: 22.95 | I32: 27 | J32: Sim | K32: https://roundlab.com/products/birch-moisturizing-sun-cushion | L32: =ROUND(H32*(1+Parâmetros!$B$2)*Parâmetros!$B$1,2) | M32: =IF(OR(D32="",L32=""),"",D32/L32-1)
A33: MB000591 | B33: Birch Moisturizing Sun Stick: protetor solar em bastão FPS 50 19 g | C33: Sim | D33: 181.9 | E33: Certeiro | F33: Birch Moisturizing Sun Stick SPF 50 | H33: 25 | J33: Sim | K33: https://roundlab.com/products/birch-moisturizing-sun-stick | L33: =ROUND(H33*(1+Parâmetros!$B$2)*Parâmetros!$B$1,2) | M33: =IF(OR(D33="",L33=""),"",D33/L33-1)
A34: MB000617 | B34: Birch Moisturizing Sunscreen UVLock: kit com 2 protetores FPS 45 de 50 ml | C34: Sim | D34: 283.9 | E34: Certeiro | F34: Birch Sunscreen + Birch Cream Duo | G34: Birch Moisturizing Cream + Birch Moisturizing Sunscreen UVLock SPF 45+ Broad Spectrum | H34: 45.74 | I34: 60.99 | J34: Sim | K34: https://roundlab.com/products/birch-sunscreen-birch-cream-duo | L34: =ROUND(H34*(1+Parâmetros!$B$2)*Parâmetros!$B$1,2) | M34: =IF(OR(D34="",L34=""),"",D34/L34-1)
A35: MB000588 | B35: Birch Moisturizing Toner Pad: discos de tônico calmantes de bétula, 80 unidades | C35: Sim | D35: 172.9 | E35: Certeiro | F35: Birch Moisturizing Toner Pad | H35: 23.8 | I35: 28 | J35: Sim | K35: https://roundlab.com/products/birch-moisturizing-pad | L35: =ROUND(H35*(1+Parâmetros!$B$2)*Parâmetros!$B$1,2) | M35: =IF(OR(D35="",L35=""),"",D35/L35-1)
A36: MB000586 | B36: Birch Moisturizing Wash Off Mask: máscara hidratante de enxágue com bétula 80 ml | C36: Sim | D36: 160.9 | E36: Certeiro | F36: Birch Moisturizing Wash Off Mask | H36: 22.1 | I36: 26 | J36: Sim | K36: https://roundlab.com/products/birch-moisturizing-wash-off-mask | L36: =ROUND(H36*(1+Parâmetros!$B$2)*Parâmetros!$B$1,2) | M36: =IF(OR(D36="",L36=""),"",D36/L36-1)
A37: MB000581 | B37: Camellia Deep Collagen Eye Cream: creme para a área dos olhos de camélia 30 ml | C37: Sim | D37: 217.9 | E37: Certeiro | F37: Camellia Deep Collagen Eye Cream 30ml | H37: 30 | J37: Sim | K37: https://roundlab.com/products/camellia-deep-collagen-eye-cream-30ml | L37: =ROUND(H37*(1+Parâmetros!$B$2)*Parâmetros!$B$1,2) | M37: =IF(OR(D37="",L37=""),"",D37/L37-1)
A38: MB000580 | B38: Camellia Deep Collagen Firming Ampoule: ampola firmadora de camélia e colágeno 30 ml | C38: Sim | D38: 232.9 | E38: Certeiro | F38: Camellia Deep Collagen Firming Ampoule | H38: 32 | J38: Sim | K38: https://roundlab.com/products/camellia-deep-collagen-firming-ampoule | L38: =ROUND(H38*(1+Parâmetros!$B$2)*Parâmetros!$B$1,2) | M38: =IF(OR(D38="",L38=""),"",D38/L38-1)
A39: MB000578 | B39: Camellia Deep Collagen Firming Cream: creme firmador de camélia e colágeno 50 ml | C39: Sim | D39: 261.9 | E39: Certeiro | F39: Camellia Deep Collagen Firming Cream | H39: 36 | J39: Sim | K39: https://roundlab.com/products/camellia-deep-collagen-firming-cream | L39: =ROUND(H39*(1+Parâmetros!$B$2)*Parâmetros!$B$1,2) | M39: =IF(OR(D39="",L39=""),"",D39/L39-1)
A40: MB000577 | B40: Camellia Deep Collagen Firming Gel Mask: máscara de hidrogel firmadora de camélia | C40: Sim | D40: 42.9 | E40: Certeiro | F40: Camellia Deep Collagen Firming Gel Mask | G40: 1 pc | H40: 6 | J40: Sim | K40: https://roundlab.com/products/camellia-deep-collagen-firming-gel-mask?variant=46577419976918 | L40: =ROUND(H40*(1+Parâmetros!$B$2)*Parâmetros!$B$1,2) | M40: =IF(OR(D40="",L40=""),"",D40/L40-1)
A41: MB000576 | B41: Camellia Deep Collagen Jelly Mask Cleanser: sabonete e máscara em geleia | C41: Sim | D41: 152.9 | E41: Certeiro | F41: Camellia Deep Collagen Jelly Mask Cleanser | H41: 21 | J41: Sim | K41: https://roundlab.com/products/camellia-deep-collagen-jelly-mask-cleanser | L41: =ROUND(H41*(1+Parâmetros!$B$2)*Parâmetros!$B$1,2) | M41: =IF(OR(D41="",L41=""),"",D41/L41-1)
A42: MB000575 | B42: Camellia Deep Collagen Milky PDRN Toner: tônico leitoso de camélia e PDRN 150 ml | C42: Sim | D42: 210.9 | E42: Certeiro | F42: Camellia Deep Collagen Milky PDRN Toner 150ml | H42: 29 | J42: Sim | K42: https://roundlab.com/products/camellia-deep-collagen-milky-pdrn-toner-150ml | L42: =ROUND(H42*(1+Parâmetros!$B$2)*Parâmetros!$B$1,2) | M42: =IF(OR(D42="",L42=""),"",D42/L42-1)
A43: MB000574 | B43: Camellia Deep Collagen V Lifting Gel Mask: máscara em gel para o contorno do queixo | C43: Sim | D43: 42.9 | E43: Certeiro | F43: Camellia Deep Collagen V Lifting Gel Mask | G43: 14PC | H43: 42.99 | J43: Esgotado | K43: https://roundlab.com/products/camellia-deep-collagen-v-lifting-gel-mask?variant=47056525787350 | L43: =ROUND(H43*(1+Parâmetros!$B$2)*Parâmetros!$B$1,2) | M43: =IF(OR(D43="",L43=""),"",D43/L43-1)
A44: MB000571 | B44: Dokdo Cleansing Water: água micelar demaquilante com água do mar profundo 400 ml | C44: Sim | D44: 128.9 | E44: Certeiro | F44: Dokdo Cleansing Water | H44: 22.4 | I44: 28 | J44: Sim | K44: https://roundlab.com/products/dokdo-cleansing-water | L44: =ROUND(H44*(1+Parâmetros!$B$2)*Parâmetros!$B$1,2) | M44: =IF(OR(D44="",L44=""),"",D44/L44-1)
A45: MB000623 | B45: Duo 1025 Dokdo: tônico hidratante 200 ml + loção hidratante 200 ml | C45: Sim | D45: 283.9 | E45: Certeiro | F45: 1025 Dokdo Toner + Lotion Duo | H45: 31.2 | I45: 39 | J45: Sim | K45: https://roundlab.com/products/1025-dokdo-toner-lotion-kit | L45: =ROUND(H45*(1+Parâmetros!$B$2)*Parâmetros!$B$1,2) | M45: =IF(OR(D45="",L45=""),"",D45/L45-1)
A46: MB000526 | B46: Kit Solar Sun-Ready Everywhere | C46: Sim | D46: 518.9 | E46: Certeiro | F46: Sun-Ready Everywhere Sun Care Bundle | H46: 71.24 | I46: 94.99 | J46: Sim | K46: https://roundlab.com/products/sun-ready-everywhere-bundle | L46: =ROUND(H46*(1+Parâmetros!$B$2)*Parâmetros!$B$1,2) | M46: =IF(OR(D46="",L46=""),"",D46/L46-1)
A47: MB000567 | B47: Mugwort Calming Cleanser: espuma de limpeza calmante de artemísia 150 ml | C47: Sim | D47: 123.9 | E47: Certeiro | F47: Mugwort Calming Cleanser | H47: 17 | J47: Sim | K47: https://roundlab.com/products/mugwort-calming-cleanser | L47: =ROUND(H47*(1+Parâmetros!$B$2)*Parâmetros!$B$1,2) | M47: =IF(OR(D47="",L47=""),"",D47/L47-1)
A48: MB000566 | B48: Mugwort Calming Cream: creme calmante leve de artemísia 80 ml | C48: Sim | D48: 261.9 | E48: Certeiro | F48: Mugwort Calming Cream | H48: 36 | J48: Sim | K48: https://roundlab.com/products/mugwort-calming-cream | L48: =ROUND(H48*(1+Parâmetros!$B$2)*Parâmetros!$B$1,2) | M48: =IF(OR(D48="",L48=""),"",D48/L48-1)
A49: MB000564 | B49: Mugwort Calming Serum: sérum calmante de artemísia e centella 50 ml | C49: Sim | D49: 225.9 | E49: Certeiro | F49: Mugwort Calming Serum | H49: 31 | J49: Sim | K49: https://roundlab.com/products/mugwort-calming-serum | L49: =ROUND(H49*(1+Parâmetros!$B$2)*Parâmetros!$B$1,2) | M49: =IF(OR(D49="",L49=""),"",D49/L49-1)
A50: MB000563 | B50: Mugwort Calming Sheet Mask: máscara em folha calmante de artemísia 25 ml | C50: Sim | D50: 28.9 | E50: Certeiro | F50: Mugwort Calming Sheet Mask | G50: 1 PC | H50: 4 | J50: Sim | K50: https://roundlab.com/products/mugwort-calming-sheet-mask?variant=43610238386390 | L50: =ROUND(H50*(1+Parâmetros!$B$2)*Parâmetros!$B$1,2) | M50: =IF(OR(D50="",L50=""),"",D50/L50-1)
A51: MB000562 | B51: Mugwort Calming Toner: tônico calmante de artemísia 300 ml | C51: Sim | D51: 195.9 | E51: Certeiro | F51: Mugwort Calming Toner | H51: 27 | J51: Sim | K51: https://roundlab.com/products/mugwort-calming-toner | L51: =ROUND(H51*(1+Parâmetros!$B$2)*Parâmetros!$B$1,2) | M51: =IF(OR(D51="",L51=""),"",D51/L51-1)
A52: MB000560 | B52: Pine Calming Cica Ampoule: ampola calmante de pinheiro e centella 30 ml | C52: Sim | D52: 181.9 | E52: Certeiro | F52: Pine Calming Cica Ampoule | H52: 25 | J52: Sim | K52: https://roundlab.com/products/pine-tree-cica-care-ampoule | L52: =ROUND(H52*(1+Parâmetros!$B$2)*Parâmetros!$B$1,2) | M52: =IF(OR(D52="",L52=""),"",D52/L52-1)
A53: MB000559 | B53: Pine Calming Cica Body Wash: sabonete líquido corporal de pinheiro e cica 400 ml | C53: Sim | D53: 174.9 | E53: Certeiro | F53: Pine Calming Cica Body Wash | H53: 24 | J53: Sim | K53: https://roundlab.com/products/pine-cica-calming-body-wash | L53: =ROUND(H53*(1+Parâmetros!$B$2)*Parâmetros!$B$1,2) | M53: =IF(OR(D53="",L53=""),"",D53/L53-1)
A54: MB000558 | B54: Pine Calming Cica Cleanser: espuma de limpeza calmante de pinheiro 150 ml | C54: Sim | D54: 123.9 | E54: Certeiro | F54: Pine Calming Cica Cleanser | H54: 17 | J54: Sim | K54: https://roundlab.com/products/pine-calming-cica-cleanser | L54: =ROUND(H54*(1+Parâmetros!$B$2)*Parâmetros!$B$1,2) | M54: =IF(OR(D54="",L54=""),"",D54/L54-1)
A55: MB000557 | B55: Pine Calming Cica Cream: creme em gel calmante de pinheiro e centella 50 ml | C55: Sim | D55: 225.9 | E55: Certeiro | F55: Pine Calming Cica Cream | H55: 31 | J55: Sim | K55: https://roundlab.com/products/pine-tree-cica-cream | L55: =ROUND(H55*(1+Parâmetros!$B$2)*Parâmetros!$B$1,2) | M55: =IF(OR(D55="",L55=""),"",D55/L55-1)
A56: MB000556 | B56: Pine Calming Cica Lotion: loção calmante leve de pinheiro e centella 250 ml | C56: Sim | D56: 203.9 | E56: Certeiro | F56: Pine Calming Cica Lotion | H56: 28 | J56: Sim | K56: https://roundlab.com/products/pine-calming-cica-lotion | L56: =ROUND(H56*(1+Parâmetros!$B$2)*Parâmetros!$B$1,2) | M56: =IF(OR(D56="",L56=""),"",D56/L56-1)
A57: MB000555 | B57: Pine Calming Cica Shampoo: shampoo calmante para couro cabeludo sensível 400 ml | C57: Sim | D57: 159.9 | E57: Certeiro | F57: Pine Calming Cica Shampoo | H57: 22 | J57: Sim | K57: https://roundlab.com/products/pine-calming-cica-shampoo | L57: =ROUND(H57*(1+Parâmetros!$B$2)*Parâmetros!$B$1,2) | M57: =IF(OR(D57="",L57=""),"",D57/L57-1)
A58: MB000554 | B58: Pine Calming Cica Sheet Mask: máscara em folha calmante de pinheiro 27 ml | C58: Sim | D58: 28.9 | E58: Certeiro | F58: Pine Calming Cica Sheet Mask | G58: 1 PC | H58: 4 | J58: Sim | K58: https://roundlab.com/products/pine-tree-cica-sheet-mask?variant=44067264561366 | L58: =ROUND(H58*(1+Parâmetros!$B$2)*Parâmetros!$B$1,2) | M58: =IF(OR(D58="",L58=""),"",D58/L58-1)
A59: MB000552 | B59: Pine Calming Cica Toner Pad: discos de tônico calmantes de pinheiro, 50 unidades | C59: Sim | D59: 203.9 | E59: Certeiro | F59: Pine Calming Cica Toner Pad | H59: 28 | J59: Sim | K59: https://roundlab.com/products/pine-tree-cica-pad | L59: =ROUND(H59*(1+Parâmetros!$B$2)*Parâmetros!$B$1,2) | M59: =IF(OR(D59="",L59=""),"",D59/L59-1)
A60: MB000550 | B60: Pine Cica Calming Nose Pack: máscara de nariz em 2 passos, 5 unidades | C60: Sim | D60: 130.9 | E60: Certeiro | F60: Pine Cica Calming Nose Deep Cleansing Mask Kit (5 pack) | H60: 18 | J60: Sim | K60: https://roundlab.com/products/pine-cica-calming-nose-deep-cleansing-mask-5-pc | L60: =ROUND(H60*(1+Parâmetros!$B$2)*Parâmetros!$B$1,2) | M60: =IF(OR(D60="",L60=""),"",D60/L60-1)
A61: MB000548 | B61: Pine Cica Calming Scalp Tonic: tônico refrescante para o couro cabeludo | C61: Sim | D61: 130.9 | E61: Certeiro | F61: Pine Cica Calming Scalp Tonic | H61: 18 | J61: Sim | K61: https://roundlab.com/products/pine-cica-calming-scalp-tonic | L61: =ROUND(H61*(1+Parâmetros!$B$2)*Parâmetros!$B$1,2) | M61: =IF(OR(D61="",L61=""),"",D61/L61-1)
A62: MB000547 | B62: Pine Cica Deep Pore Clay Mask Cleanser: sabonete e máscara de argila 150 ml | C62: Sim | D62: 152.9 | E62: Certeiro | F62: Pine Cica Deep Pore Clay Mask Cleanser | H62: 21 | J62: Sim | K62: https://roundlab.com/products/pine-cica-deep-pore-clay-mask-cleanser | L62: =ROUND(H62*(1+Parâmetros!$B$2)*Parâmetros!$B$1,2) | M62: =IF(OR(D62="",L62=""),"",D62/L62-1)
A63: MB000546 | B63: Pine Cica Deep Pore Cleansing Oil: óleo de limpeza para poros com pinheiro 200 ml | C63: Sim | D63: 181.9 | E63: Certeiro | F63: Pine Cica Deep Pore Cleansing Oil 200ml | H63: 25 | J63: Sim | K63: https://roundlab.com/products/pine-cica-deep-pore-cleansing-oil-200ml | L63: =ROUND(H63*(1+Parâmetros!$B$2)*Parâmetros!$B$1,2) | M63: =IF(OR(D63="",L63=""),"",D63/L63-1)
A64: MB000542 | B64: Soybean Nourishing Cleanser: espuma de limpeza esfoliante de soja 150 ml | C64: Sim | D64: 108.9 | E64: Certeiro | F64: Soybean Nourishing Cleanser | H64: 17 | J64: Sim | K64: https://roundlab.com/products/soybean-nourishing-cleanser | L64: =ROUND(H64*(1+Parâmetros!$B$2)*Parâmetros!$B$1,2) | M64: =IF(OR(D64="",L64=""),"",D64/L64-1)
A65: MB000541 | B65: Soybean Nourishing Cleansing Oil: óleo de limpeza nutritivo de soja 200 ml | C65: Sim | D65: 188.9 | E65: Certeiro | F65: Soybean Nourishing Cleansing Oil | H65: 26 | J65: Sim | K65: https://roundlab.com/products/soybean-nourishing-cleansing-oil | L65: =ROUND(H65*(1+Parâmetros!$B$2)*Parâmetros!$B$1,2) | M65: =IF(OR(D65="",L65=""),"",D65/L65-1)
A66: MB000540 | B66: Soybean Nourishing Cream: creme nutritivo de soja preta 80 ml | C66: Sim | D66: 261.9 | E66: Certeiro | F66: Soybean Nourishing Cream | H66: 36 | J66: Sim | K66: https://roundlab.com/products/soybean-nourishing-cream | L66: =ROUND(H66*(1+Parâmetros!$B$2)*Parâmetros!$B$1,2) | M66: =IF(OR(D66="",L66=""),"",D66/L66-1)
A67: MB000539 | B67: Soybean Nourishing Serum: sérum nutritivo de soja com vitaminas B 50 ml | C67: Sim | D67: 225.9 | E67: Certeiro | F67: Soybean Nourishing Serum | H67: 31 | J67: Sim | K67: https://roundlab.com/products/soybean-nourishing-serum | L67: =ROUND(H67*(1+Parâmetros!$B$2)*Parâmetros!$B$1,2) | M67: =IF(OR(D67="",L67=""),"",D67/L67-1)
A68: MB000538 | B68: Soybean Nourishing Sheet Mask: máscara em folha nutritiva de soja preta 27 ml | C68: Sim | D68: 28.9 | E68: Certeiro | F68: Soybean Nourishing Sheet Mask | G68: 1 PC | H68: 4 | J68: Sim | K68: https://roundlab.com/products/soybean-nourishing-sheet-mask?variant=43610248020182 | L68: =ROUND(H68*(1+Parâmetros!$B$2)*Parâmetros!$B$1,2) | M68: =IF(OR(D68="",L68=""),"",D68/L68-1)
A69: MB000537 | B69: Soybean Nourishing Toner: tônico nutritivo de soja preta 300 ml | C69: Sim | D69: 195.9 | E69: Certeiro | F69: Soybean Nourishing Toner | H69: 27 | J69: Sim | K69: https://roundlab.com/products/soybean-nourishing-toner | L69: =ROUND(H69*(1+Parâmetros!$B$2)*Parâmetros!$B$1,2) | M69: =IF(OR(D69="",L69=""),"",D69/L69-1)
A70: MB000535 | B70: Soybean Panthenol Ampoule: ampola de soja preta e pantenol 50 ml | C70: Sim | D70: 246.9 | E70: Certeiro | F70: Soybean Panthenol Ampoule | H70: 34 | J70: Sim | K70: https://roundlab.com/products/soybean-panthenol-ampoule | L70: =ROUND(H70*(1+Parâmetros!$B$2)*Parâmetros!$B$1,2) | M70: =IF(OR(D70="",L70=""),"",D70/L70-1)
A71: MB000534 | B71: Soybean Panthenol Cleanser: espuma de limpeza de pH 5,5 com soja e pantenol | C71: Sim | D71: 123.9 | E71: Certeiro | F71: Soybean Panthenol Cleanser | H71: 17 | J71: Sim | K71: https://roundlab.com/products/soybean-panthenol-cleanser | L71: =ROUND(H71*(1+Parâmetros!$B$2)*Parâmetros!$B$1,2) | M71: =IF(OR(D71="",L71=""),"",D71/L71-1)
A72: MB000533 | B72: Soybean Panthenol Cleansing Oil: óleo de limpeza de soja e pantenol | C72: Sim | D72: 181.9 | E72: Certeiro | F72: Soybean Panthenol Cleansing Oil | H72: 25 | J72: Sim | K72: https://roundlab.com/products/soybean-panthenol-cleansing-oil | L72: =ROUND(H72*(1+Parâmetros!$B$2)*Parâmetros!$B$1,2) | M72: =IF(OR(D72="",L72=""),"",D72/L72-1)
A73: MB000532 | B73: Soybean Panthenol Cream: creme de soja preta e pantenol para a barreira 80 ml | C73: Sim | D73: 276.9 | E73: Certeiro | F73: Soybean Panthenol Cream | H73: 38 | J73: Sim | K73: https://roundlab.com/products/soybean-panthenol-cream | L73: =ROUND(H73*(1+Parâmetros!$B$2)*Parâmetros!$B$1,2) | M73: =IF(OR(D73="",L73=""),"",D73/L73-1)
A74: MB000530 | B74: Soybean Panthenol Sheet Mask: máscara em folha de soja preta e pantenol 27 ml | C74: Sim | D74: 28.9 | E74: Certeiro | F74: Soybean Panthenol Sheet Mask | G74: 1 PC | H74: 3.99 | J74: Sim | K74: https://roundlab.com/products/soybean-panthenol-mask?variant=45086692901078 | L74: =ROUND(H74*(1+Parâmetros!$B$2)*Parâmetros!$B$1,2) | M74: =IF(OR(D74="",L74=""),"",D74/L74-1)
A75: MB000528 | B75: Soybean Panthenol Toner: tônico de soja preta e pantenol para a barreira 200 ml | C75: Sim | D75: 181.9 | E75: Certeiro | F75: Soybean Panthenol Toner | H75: 25 | J75: Sim | K75: https://roundlab.com/products/soybean-panthenol-toner | L75: =ROUND(H75*(1+Parâmetros!$B$2)*Parâmetros!$B$1,2) | M75: =IF(OR(D75="",L75=""),"",D75/L75-1)
A76: MB000525 | B76: Vita Niacinamide Dark Spot Cream: creme de niacinamida para tom uniforme | C76: Sim | D76: 239.9 | E76: Certeiro | F76: Vita Niacinamide Dark Spot Cream | H76: 33 | J76: Sim | K76: https://roundlab.com/products/vita-niacinamide-dark-spot-cream | L76: =ROUND(H76*(1+Parâmetros!$B$2)*Parâmetros!$B$1,2) | M76: =IF(OR(D76="",L76=""),"",D76/L76-1)
A77: MB000523 | B77: Vita Niacinamide Dark Spot Serum Mask: máscara em folha de niacinamida 20 ml | C77: Sim | D77: 37.9 | E77: Certeiro | F77: Vita Niacinamide Dark Spot Serum Mask | G77: 1 PC | H77: 5.3 | J77: Sim | K77: https://roundlab.com/products/vita-niacinamide-dark-spot-mask?variant=46537314369750 | L77: =ROUND(H77*(1+Parâmetros!$B$2)*Parâmetros!$B$1,2) | M77: =IF(OR(D77="",L77=""),"",D77/L77-1)
A78: MB000521 | B78: Vita Niacinamide Glow Capsule Cream: gel-creme de niacinamida com cápsulas 50 ml | C78: Sim | D78: 203.9 | E78: Certeiro | F78: Vita Niacinamide Glow Capsule Cream | H78: 28 | J78: Esgotado | K78: https://roundlab.com/products/vita-niacinamide-glow-capsule-cream | L78: =ROUND(H78*(1+Parâmetros!$B$2)*Parâmetros!$B$1,2) | M78: =IF(OR(D78="",L78=""),"",D78/L78-1)
A79: MB003118 | B79: 1025 Dokdo Toner 200ml | C79: Não | D79: 42.9 | E79: Certeiro | F79: 1025 Dokdo Toner | G79: 200ml | H79: 13.6 | I79: 17 | J79: Sim | K79: https://roundlab.com/products/1025-dokdo-toner?variant=43023567749334 | L79: =ROUND(H79*(1+Parâmetros!$B$2)*Parâmetros!$B$1,2) | M79: =IF(OR(D79="",L79=""),"",D79/L79-1)
A80: MB003124 | B80: 1025 Dokdo Cleansing Milk: leite de limpeza hidratante 200 ml | C80: Sim | D80: 128.9 | E80: Provável — conferir | F80: 1025 Dokdo Cleansing Gel | H80: 20.8 | I80: 26 | J80: Sim | K80: https://roundlab.com/products/1025-dokdo-cleansing-gel | L80: =ROUND(H80*(1+Parâmetros!$B$2)*Parâmetros!$B$1,2) | M80: =IF(OR(D80="",L80=""),"",D80/L80-1)
A81: MB003104 | B81: 1025 Dokdo Eye Cream: creme hidratante para a área dos olhos 30 ml | C81: Sim | D81: 104.9 | E81: Provável — conferir | F81: 1025 Dokdo Cream | H81: 28.8 | I81: 36 | J81: Sim | K81: https://roundlab.com/products/1025-dokdo-cream | L81: =ROUND(H81*(1+Parâmetros!$B$2)*Parâmetros!$B$1,2) | M81: =IF(OR(D81="",L81=""),"",D81/L81-1)
A82: MB003096 | B82: 1025 Dokdo Toner: kit com 2 tônicos (200 ml + 500 ml) | C82: Sim | D82: 371.9 | E82: Provável — conferir | F82: 1025 Dokdo Cleanser + Dokdo Toner 200ml | H82: 34 | J82: Sim | K82: https://roundlab.com/products/dokdo-cleanser-dokdo-toner-the-perfect-gentle-routine | L82: =ROUND(H82*(1+Parâmetros!$B$2)*Parâmetros!$B$1,2) | M82: =IF(OR(D82="",L82=""),"",D82/L82-1)
A83: MB000624 | B83: 1025 Dokdo Toner: tônico hidratante com esfoliação suave e água do mar profundo | C83: Sim | D83: 42.9 | E83: Provável — conferir | F83: 1025 Dokdo Toner Pad | H83: 21.6 | I83: 27 | J83: Sim | K83: https://roundlab.com/products/1025-dokdo-pad | L83: =ROUND(H83*(1+Parâmetros!$B$2)*Parâmetros!$B$1,2) | M83: =IF(OR(D83="",L83=""),"",D83/L83-1)
A84: MB003969 | B84: 1025 Dokdo: kit triplo de limpeza (150 ml × 3) | C84: Sim | D84: 371.9 | E84: Provável — conferir | F84: 1025 Dokdo Toner + Lotion Duo | H84: 31.2 | I84: 39 | J84: Sim | K84: https://roundlab.com/products/1025-dokdo-toner-lotion-kit | L84: =ROUND(H84*(1+Parâmetros!$B$2)*Parâmetros!$B$1,2) | M84: =IF(OR(D84="",L84=""),"",D84/L84-1)
A85: MB004048 | B85: Birch Juice Moisturizing Sunscreen: protetor solar hidratante 50 ml (kit com 3) | C85: Sim | D85: 363.9 | E85: Provável — conferir | F85: Birch Sunscreen + Birch Cream Duo | G85: Birch Moisturizing Cream + Birch Moisturizing Sunscreen UVLock SPF 45+ Broad Spectrum | H85: 45.74 | I85: 60.99 | J85: Sim | K85: https://roundlab.com/products/birch-sunscreen-birch-cream-duo | L85: =ROUND(H85*(1+Parâmetros!$B$2)*Parâmetros!$B$1,2) | M85: =IF(OR(D85="",L85=""),"",D85/L85-1)
A86: MB000604 | B86: Birch Mild-Up Sunscreen UVLock: protetor solar mineral FPS 50 50 ml | C86: Sim | D86: 181.9 | E86: Provável — conferir | F86: Birch Mild-Up Sunscreen UVLock SPF 50 Broad Spectrum | H86: 24.99 | J86: Sim | K86: https://roundlab.com/products/birch-juice-mild-up-uvlock-sunscreen | L86: =ROUND(H86*(1+Parâmetros!$B$2)*Parâmetros!$B$1,2) | M86: =IF(OR(D86="",L86=""),"",D86/L86-1)
A87: MB000602 | B87: Birch Moisturizing Cream: creme hidratante leve de seiva de bétula 80 ml | C87: Sim | D87: 222.9 | E87: Provável — conferir | F87: Birch Moisturizing Cream | H87: 30.6 | I87: 36 | J87: Sim | K87: https://roundlab.com/products/birch-moisturizing-cream | L87: =ROUND(H87*(1+Parâmetros!$B$2)*Parâmetros!$B$1,2) | M87: =IF(OR(D87="",L87=""),"",D87/L87-1)
A88: MB000601 | B88: Birch Moisturizing Cream: kit com 2 cremes hidratantes de bétula de 80 ml | C88: Sim | D88: 524.9 | E88: Provável — conferir | F88: Birch Sunscreen + Birch Cream Duo | G88: Birch Moisturizing Cream + Birch Moisturizing Sunscreen UVLock SPF 45+ Broad Spectrum | H88: 45.74 | I88: 60.99 | J88: Sim | K88: https://roundlab.com/products/birch-sunscreen-birch-cream-duo | L88: =ROUND(H88*(1+Parâmetros!$B$2)*Parâmetros!$B$1,2) | M88: =IF(OR(D88="",L88=""),"",D88/L88-1)
A89: MB000595 | B89: Birch Moisturizing Serum: sérum hidratante de seiva de bétula 50 ml | C89: Sim | D89: 191.9 | E89: Provável — conferir | F89: Birch Moisturizing Serum | H89: 26.35 | I89: 31 | J89: Esgotado | K89: https://roundlab.com/products/birch-moisturizing-serum | L89: =ROUND(H89*(1+Parâmetros!$B$2)*Parâmetros!$B$1,2) | M89: =IF(OR(D89="",L89=""),"",D89/L89-1)
A90: MB000590 | B90: Birch Moisturizing Sunscreen UVLock: protetor solar hidratante FPS 45 50 ml | C90: Sim | D90: 181.9 | E90: Provável — conferir | F90: Birch Moisturizing Sunscreen UVLock SPF 50 Broad Spectrum | H90: 24.99 | J90: Sim | K90: https://roundlab.com/products/birch-moisturizing-uv-sunscreen | L90: =ROUND(H90*(1+Parâmetros!$B$2)*Parâmetros!$B$1,2) | M90: =IF(OR(D90="",L90=""),"",D90/L90-1)
A91: MB000589 | B91: Birch Moisturizing Toner: tônico hidratante de seiva de bétula 300 ml | C91: Sim | D91: 195.9 | E91: Provável — conferir | F91: Birch Moisturizing Toner | H91: 27 | J91: Sim | K91: https://roundlab.com/products/birch-moisturizing-toner | L91: =ROUND(H91*(1+Parâmetros!$B$2)*Parâmetros!$B$1,2) | M91: =IF(OR(D91="",L91=""),"",D91/L91-1)
A92: MB000585 | B92: Duo Birch: protetor solar hidratante FPS 45 50 ml + creme hidratante 80 ml | C92: Sim | D92: 332.9 | E92: Provável — conferir | F92: Birch Sunscreen + Birch Cream Duo | G92: Birch Moisturizing Cream + Birch Moisturizing Sunscreen UVLock SPF 45+ Broad Spectrum | H92: 45.74 | I92: 60.99 | J92: Sim | K92: https://roundlab.com/products/birch-sunscreen-birch-cream-duo | L92: =ROUND(H92*(1+Parâmetros!$B$2)*Parâmetros!$B$1,2) | M92: =IF(OR(D92="",L92=""),"",D92/L92-1)
A93: MB003123 | B93: For Men Birch Moisturizing Toner: tônico hidratante masculino de bétula 200 ml | C93: Sim | D93: 128.9 | E93: Provável — conferir | F93: Birch Moisturizing Toner | H93: 27 | J93: Sim | K93: https://roundlab.com/products/birch-moisturizing-toner | L93: =ROUND(H93*(1+Parâmetros!$B$2)*Parâmetros!$B$1,2) | M93: =IF(OR(D93="",L93=""),"",D93/L93-1)
A94: MB003037 | B94: For Men Pine Calming Cica Cream: creme em gel calmante masculino de pinheiro 75 ml | C94: Sim | D94: 144.9 | E94: Provável — conferir | F94: Pine Calming Cica Cream | H94: 31 | J94: Sim | K94: https://roundlab.com/products/pine-tree-cica-cream | L94: =ROUND(H94*(1+Parâmetros!$B$2)*Parâmetros!$B$1,2) | M94: =IF(OR(D94="",L94=""),"",D94/L94-1)
A95: MB003036 | B95: For Men Pine Calming Cica Lotion: loção calmante masculina de pinheiro 200 ml | C95: Sim | D95: 133.9 | E95: Provável — conferir | F95: Pine Calming Cica Lotion | H95: 28 | J95: Sim | K95: https://roundlab.com/products/pine-calming-cica-lotion | L95: =ROUND(H95*(1+Parâmetros!$B$2)*Parâmetros!$B$1,2) | M95: =IF(OR(D95="",L95=""),"",D95/L95-1)
A96: MB000633 | B96: Kit 1025 Dokdo: espuma de limpeza 150 ml + tônico 200 ml | C96: Sim | D96: 246.9 | E96: Provável — conferir | F96: 1025 Dokdo Toner + Lotion Duo | H96: 31.2 | I96: 39 | J96: Sim | K96: https://roundlab.com/products/1025-dokdo-toner-lotion-kit | L96: =ROUND(H96*(1+Parâmetros!$B$2)*Parâmetros!$B$1,2) | M96: =IF(OR(D96="",L96=""),"",D96/L96-1)
A97: MB003069 | B97: Kit 1025 Dokdo: tônico 500 ml + loção hidratante 200 ml | C97: Sim | D97: 358.9 | E97: Provável — conferir | F97: 1025 Dokdo Toner + Lotion Duo | H97: 31.2 | I97: 39 | J97: Sim | K97: https://roundlab.com/products/1025-dokdo-toner-lotion-kit | L97: =ROUND(H97*(1+Parâmetros!$B$2)*Parâmetros!$B$1,2) | M97: =IF(OR(D97="",L97=""),"",D97/L97-1)
A98: MB000583 | B98: Kit Camellia Deep Collagen: ampola 30 ml + creme 50 ml + máscara de brinde | C98: Sim | D98: 403.9 | E98: Provável — conferir | F98: Camellia Collagen Slow Aging Routine | G98: Camellia Deep Collagen Firming Ampoule + Camellia Deep Collagen Firming Cream + 4 pc Camellia Deep Collagen Firming Gel Mask + Camellia Deep Collagen Jelly Mask Cleanser + 1 PC Camellia Deep Collagen V Lifting Gel Mask | H98: 87.74 | I98: 116.99 | J98: Sim | K98: https://roundlab.com/products/camellia-collagen-slow-aging-routine | L98: =ROUND(H98*(1+Parâmetros!$B$2)*Parâmetros!$B$1,2) | M98: =IF(OR(D98="",L98=""),"",D98/L98-1)
A99: MB000527 | B99: Kit Soybean Panthenol: ampola 50 ml + creme 80 ml + máscara de brinde | C99: Sim | D99: 523.9 | E99: Provável — conferir | F99: Soybean Panthenol Double Cleansing Bundle | G99: 1 PC Soybean Panthenol Mask + Soybean Panthenol Cleanser + Soybean Panthenol Cleansing Oil | H99: 41.39 | I99: 45.99 | J99: Sim | K99: https://roundlab.com/products/soybean-panthenol-double-cleansing-bundle | L99: =ROUND(H99*(1+Parâmetros!$B$2)*Parâmetros!$B$1,2) | M99: =IF(OR(D99="",L99=""),"",D99/L99-1)
A100: MB000522 | B100: Kit Vita Niacinamide: sérum 30 ml + creme + máscara em folha de brinde | C100: Sim | D100: 378.9 | E100: Provável — conferir | F100: Vita Niacinamide Glass Skin Routine Bundle | H100: 51.98 | I100: 69.3 | J100: Sim | K100: https://roundlab.com/products/vita-niacinamide-brightening-routine-set | L100: =ROUND(H100*(1+Parâmetros!$B$2)*Parâmetros!$B$1,2) | M100: =IF(OR(D100="",L100=""),"",D100/L100-1)
...

Sheet Catálogo oficial
A1: Produto oficial | B1: Variante | C1: Preço (US$) | D1: Preço cheio (US$) | E1: Disponível? | F1: Kit/combo? | G1: SKU deles | H1: Link
A2: 1025 Dokdo Ampoule | C2: 24.8 | D2: 31 | E2: Sim | G2: XI-SV70-130S | H2: https://roundlab.com/products/1025-dokdo-ampoule
A3: 1025 Dokdo Cleanser | C3: 13.6 | D3: 17 | E3: Sim | G3: RL1025DCL | H3: https://roundlab.com/products/1025-dokdo-cleanser
A4: 1025 Dokdo Cleanser + Dokdo Toner 200ml | C4: 34 | E4: Sim | F4: Sim | G4: RLTPGR | H4: https://roundlab.com/products/dokdo-cleanser-dokdo-toner-the-perfect-gentle-routine
A5: 1025 Dokdo Cleansing Balm 50ml | B5: 50ml | C5: 22.4 | D5: 28 | E5: Sim | G5: RC01W0001 | H5: https://roundlab.com/products/1025-dokdo-cleansing-balm-50ml
A6: 1025 Dokdo Cleansing Gel | C6: 20.8 | D6: 26 | E6: Sim | G6: RLCLGEL | H6: https://roundlab.com/products/1025-dokdo-cleansing-gel
A7: 1025 Dokdo Cleansing Oil | C7: 20.8 | D7: 26 | E7: Sim | G7: RLDCLO200 | H7: https://roundlab.com/products/1025-dokdo-cleansing-oil
A8: 1025 Dokdo Cream | C8: 28.8 | D8: 36 | E8: Sim | G8: 1025RLC80 | H8: https://roundlab.com/products/1025-dokdo-cream
A9: 1025 Dokdo Lotion | C9: 17.6 | D9: 22 | E9: Sim | G9: RLDL200 | H9: https://roundlab.com/products/1025-dokdo-lotion
A10: 1025 Dokdo Mud Pack | C10: 15.2 | D10: 19 | E10: Sim | G10: RLDMP100 | H10: https://roundlab.com/products/1025-dokdo-mud-pack
A11: 1025 Dokdo Peeling Gel | C11: 19.2 | D11: 24 | E11: Sim | G11: RL1025PEELGEL | H11: https://roundlab.com/products/1025-dokdo-peeling-gel
A12: 1025 Dokdo Sleeping Pack | C12: 19.2 | D12: 24 | E12: Sim | G12: RL1025DSP100 | H12: https://roundlab.com/products/1025-dokdo-sleeping-pack
A13: 1025 Dokdo Toner + Lotion Duo | C13: 31.2 | D13: 39 | E13: Sim | F13: Sim | G13: RLDTDL200 | H13: https://roundlab.com/products/1025-dokdo-toner-lotion-kit
A14: 1025 Dokdo Toner Pad | C14: 21.6 | D14: 27 | E14: Sim | G14: RLDDPD | H14: https://roundlab.com/products/1025-dokdo-pad
A15: 1025 Dokdo Toner | B15: 100ml | C15: 8 | D15: 10 | E15: Sim | G15: RLDT100ML | H15: https://roundlab.com/products/1025-dokdo-toner?variant=43023567716566
A16: 1025 Dokdo Toner | B16: 200ml | C16: 13.6 | D16: 17 | E16: Sim | G16: RL1025DT200 | H16: https://roundlab.com/products/1025-dokdo-toner?variant=43023567749334
A17: 1025 Dokdo Toner | B17: 500ml | C17: 27.2 | D17: 34 | E17: Sim | G17: RLDT500ML | H17: https://roundlab.com/products/1025-dokdo-toner?variant=43023567782102
A18: 1025 Dokdo Toner | B18: 50ml | C18: 4.8 | D18: 6 | E18: Esgotado | H18: https://roundlab.com/products/1025-dokdo-toner?variant=47927553425622
A19: 1025 Dokdo Trio | B19: 200ml 1025 Dokdo Toner + 1025 Dokdo Lotion + 1025 Dokdo Cleanser | C19: 42 | D19: 56 | E19: Sim | F19: Sim | G19: 9b83b170-1e2a-411e-be81-50df714f62f0 | H19: https://roundlab.com/products/dokdo-trio
A20: 1025 Dokdo Water Gel Mask Sheet | B20: 1 PC | C20: 3.2 | D20: 4 | E20: Sim | G20: RL1025DWGHM30 | H20: https://roundlab.com/products/1025-dokdo-mask-sheet?variant=44067260465366
A21: 1025 Dokdo Water Gel Mask Sheet | B21: 10 PC | C21: 28.8 | D21: 36 | E21: Sim | G21: RL1025DWGHM32 | H21: https://roundlab.com/products/1025-dokdo-mask-sheet?variant=43734061711574
A22: 1025 Dokdo Water Gel Mask Sheet | B22: 5 PC | C22: 15.2 | D22: 19 | E22: Sim | G22: RL1025DWGHM31 | H22: https://roundlab.com/products/1025-dokdo-mask-sheet?variant=43610233471190
A23: Anti-Aging Sheet Mask Bundle | B23: 10 PC Soybean Panthenol Sheet Mask + 10 PC Vita Niacinamide Dark Spot Serum Mask + 4 pc Camellia Deep Collagen Firming Gel Mask + 4PC Camellia Deep Collagen V Lifting Gel Mask | C23: 99.22 | D23: 132.29 | E23: Sim | F23: Sim | G23: 7bbcbf74-55ed-466a-b8ed-46181be98f67 | H23: https://roundlab.com/products/anti-aging-sheet-mask-bundle
A24: Award Winning Favorites Morning Routine | B24: 200ml 1025 Dokdo Toner + 1025 Dokdo Cleanser + Birch Moisturizing Cream + Pine Calming Cica Ampoule + [Gift] 1025 Dokdo Water Gel Sheet Mask + Birch Moisturizing Sunscreen UVLock SPF 45+ Broad Spectrum | C24: 93.37 | D24: 124.49 | E24: Sim | F24: Sim | G24: 36dfe098-23d5-4d42-ba3a-8b454e8d1efd | H24: https://roundlab.com/products/award-winning-favorites-routine
A25: Award Winning Favorites Night Routine | B25: 200ml 1025 Dokdo Toner + 1025 Dokdo Cleanser + 1025 Dokdo Cleansing Oil + Birch Moisturizing Cream + Pine Calming Cica Ampoule + [Gift] 1025 Dokdo Water Gel Sheet Mask | C25: 94.13 | D25: 125.5 | E25: Sim | F25: Sim | G25: 48d654f4-9a77-4b86-8eac-a4a26866167d | H25: https://roundlab.com/products/award-winning-favorites-night-routine
A26: Birch Clear and Balanced Skin Routine + Lip Balm Brush Set | C26: 106.08 | D26: 125.39 | E26: Sim | F26: Sim | H26: https://roundlab.com/products/birch-clear-and-balanced-skin-routine-lip-balm-brush-set
A27: Birch Clear and Balanced Skin Routine | B27: Birch Moisturizing Cream + Birch Moisturizing Cleanser + Birch Moisturizing Toner + Birch Juice Moisturizing Ampoule + 1 pc Birch Moisturizing Double Gel Mask + Birch Moisturizing Lip Balm | C27: 102.74 | D27: 136.99 | E27: Esgotado | F27: Sim | G27: a592bf67-49cb-4dff-8533-bfdcbdfda9f0 | H27: https://roundlab.com/products/birch-clear-balance-routine
A28: Birch Juice Cleansing Pad | C28: 24 | E28: Sim | G28: RLBCNPD | H28: https://roundlab.com/products/birch-juice-cleansing-pad
A29: Birch Juice Moisturizing Ampoule | C29: 26.35 | D29: 31 | E29: Sim | G29: RLBCMJA | H29: https://roundlab.com/products/birch-juice-ampoule
A30: Birch Juice Moisturizing Peeling Cleansing Oil | C30: 25 | E30: Sim | G30: RC02W0001 | H30: https://roundlab.com/products/birch-juice-moisturizing-peeling-cleansing-oil
A31: Birch Juice Moisturizing Sun Serum SPF 50 | C31: 24.99 | E31: Sim | G31: RU02G0044 | H31: https://roundlab.com/products/birch-juice-moisturizing-sun-serum-spf50
A32: Birch Mild-Up Sunscreen UVLock SPF 50 Broad Spectrum | C32: 24.99 | E32: Sim | G32: RLB119V03 | H32: https://roundlab.com/products/birch-juice-mild-up-uvlock-sunscreen
A33: Birch Moisturizing Cleanser | C33: 14.45 | D33: 17 | E33: Sim | G33: RLBJMCL150 | H33: https://roundlab.com/products/birch-moisturizing-cleanser
A34: Birch Moisturizing Cream | C34: 30.6 | D34: 36 | E34: Sim | G34: RLBJMC80 | H34: https://roundlab.com/products/birch-moisturizing-cream
A35: Birch Moisturizing Cream Double Pack | C35: 72 | E35: Sim | H35: https://roundlab.com/products/birch-moisturizing-cream-2-pack
A36: Birch Moisturizing Double Gel Mask | B36: 1 pc | C36: 3.99 | E36: Sim | G36: RM02N0010 | H36: https://roundlab.com/products/birch-moisturizing-gel-mask?variant=47156793704662
A37: Birch Moisturizing Double Gel Mask | B37: 10 pc | C37: 30.6 | D37: 36 | E37: Sim | G37: RM02N0012 | H37: https://roundlab.com/products/birch-moisturizing-gel-mask?variant=47156793639126
A38: Birch Moisturizing Double Gel Mask | B38: 5 pc | C38: 16.15 | D38: 19 | E38: Sim | G38: RM02N0011 | H38: https://roundlab.com/products/birch-moisturizing-gel-mask?variant=47156793671894
A39: Birch Moisturizing Eye Balm | C39: 22 | E39: Sim | G39: RS02G0018 | H39: https://roundlab.com/products/round-lab-birch-juice-moisturizing-eye-balm-10g
A40: Birch Moisturizing Hand Cream | C40: 8.5 | E40: Sim | G40: RS02G0010 | H40: https://roundlab.com/products/birch-moisturizing-hand-cream
A41: Birch Moisturizing Intensive Cream | C41: 40 | E41: Sim | G41: RS02W0004 | H41: https://roundlab.com/products/birch-moisturizing-intensive-cream
A42: Birch Moisturizing Lip Balm | C42: 18.7 | D42: 22 | E42: Esgotado | G42: RS02W0001 | H42: https://roundlab.com/products/birch-moisturizing-lip-balm
A43: Birch Moisturizing Serum | C43: 26.35 | D43: 31 | E43: Esgotado | G43: RLBJMS50 | H43: https://roundlab.com/products/birch-moisturizing-serum
A44: Birch Moisturizing Sheet Mask | B44: 1 PC | C44: 3.4 | D44: 4 | E44: Sim | G44: RLBJSM25 | H44: https://roundlab.com/products/birch-moisturizing-sheet-mask?variant=43610237173974
A45: Birch Moisturizing Sheet Mask | B45: 10 PC | C45: 34 | D45: 40 | E45: Sim | G45: RLBJSM27 | H45: https://roundlab.com/products/birch-moisturizing-sheet-mask?variant=43734069641430
A46: Birch Moisturizing Sheet Mask | B46: 5 PC | C46: 16.15 | D46: 19 | E46: Sim | G46: RLBJSM26 | H46: https://roundlab.com/products/birch-moisturizing-sheet-mask?variant=43610237206742
A47: Birch Moisturizing Soothing Gel | C47: 14 | E47: Sim | G47: RLBJSOOTHGEL | H47: https://roundlab.com/products/birch-moisturizing-soothing-gel
A48: Birch Moisturizing Sun Cushion SPF 50 | C48: 22.95 | D48: 27 | E48: Sim | G48: RLBJSC | H48: https://roundlab.com/products/birch-moisturizing-sun-cushion
A49: Birch Moisturizing Sun Stick SPF 50 | C49: 25 | E49: Sim | G49: RLBJSS | H49: https://roundlab.com/products/birch-moisturizing-sun-stick
A50: Birch Moisturizing Sunscreen UVLock SPF 50 Broad Spectrum | C50: 24.99 | E50: Sim | G50: RLB119V02 | H50: https://roundlab.com/products/birch-moisturizing-uv-sunscreen
A51: Birch Moisturizing Toner | C51: 27 | E51: Sim | G51: RLBJT300 | H51: https://roundlab.com/products/birch-moisturizing-toner
A52: Birch Moisturizing Toner Pad | C52: 23.8 | D52: 28 | E52: Sim | G52: RLBJMP80 | H52: https://roundlab.com/products/birch-moisturizing-pad
A53: Birch Moisturizing Wash Off Mask | C53: 22.1 | D53: 26 | E53: Sim | G53: RLBJWOP | H53: https://roundlab.com/products/birch-moisturizing-wash-off-mask
A54: Birch Sunscreen + Birch Cream Duo | B54: Birch Moisturizing Cream + Birch Moisturizing Sunscreen UVLock SPF 45+ Broad Spectrum | C54: 45.74 | D54: 60.99 | E54: Sim | F54: Sim | G54: acc74c10-191e-4006-9a3c-974fcd227ae4 | H54: https://roundlab.com/products/birch-sunscreen-birch-cream-duo
A55: Birch Sunscreen Mini 10ml | C55: 6.99 | E55: Sim | H55: https://roundlab.com/products/mini-birch-sunscreen
A56: Birch Sunscreen Trio | C56: 60.74 | D56: 80.99 | E56: Sim | F56: Sim | G56: 36af67f5-7333-40b2-bd65-ffacefba9b25 | H56: https://roundlab.com/products/birch-sunscreen-trio
A57: Camellia Collagen Anti-Aging Routine Bundle | C57: 55.5 | D57: 74 | E57: Sim | F57: Sim | G57: d545d934-cc0f-4852-bcf2-80f756b247ea | H57: https://roundlab.com/products/collagen-anti-aging-routine-bundle
A58: Camellia Collagen Slow Aging Routine | B58: Camellia Deep Collagen Firming Ampoule + Camellia Deep Collagen Firming Cream + 4 pc Camellia Deep Collagen Firming Gel Mask + Camellia Deep Collagen Jelly Mask Cleanser + 1 PC Camellia Deep Collagen V Lifting Gel Mask | C58: 87.74 | D58: 116.99 | E58: Sim | F58: Sim | G58: b99ccdb4-2fc8-4a14-947b-24465ac592ae | H58: https://roundlab.com/products/camellia-collagen-slow-aging-routine
A59: Camellia Deep Collagen Eye Cream 30ml | C59: 30 | E59: Sim | G59: RS14W0002 | H59: https://roundlab.com/products/camellia-deep-collagen-eye-cream-30ml
A60: Camellia Deep Collagen Firming Ampoule | C60: 32 | E60: Sim | G60: RLB109V07 | H60: https://roundlab.com/products/camellia-deep-collagen-firming-ampoule
A61: Camellia Deep Collagen Firming Complete Routine Anti-Aging Bundle | B61: Camellia Deep Collagen Firming Ampoule + Camellia Deep Collagen Firming Cream + 4 pc Camellia Deep Collagen Firming Gel Mask + Camellia Deep Collagen Jelly Mask Cleanser + 1 PC Camellia Deep Collagen V Lifting Gel Mask + Camellia Deep Collagen Eye Crea... | C61: 140.79 | D61: 175.99 | E61: Esgotado | F61: Sim | G61: 53a2d331-4137-42e9-ad29-b42085583b08 | H61: https://roundlab.com/products/camellia-deep-collagen-firming-complete-routine-anti-aging-bundle
A62: Camellia Deep Collagen Firming Cream | C62: 36 | E62: Sim | G62: RLB104V07 | H62: https://roundlab.com/products/camellia-deep-collagen-firming-cream
A63: Camellia Deep Collagen Firming Gel Mask | B63: 1 pc | C63: 6 | E63: Sim | G63: RLB108V02 | H63: https://roundlab.com/products/camellia-deep-collagen-firming-gel-mask?variant=46577419976918
A64: Camellia Deep Collagen Firming Gel Mask | B64: 4 pc | C64: 22 | E64: Sim | G64: RLB108V01 | H64: https://roundlab.com/products/camellia-deep-collagen-firming-gel-mask?variant=46577420009686
A65: Camellia Deep Collagen Jelly Mask Cleanser | C65: 21 | E65: Sim | G65: RC14W0001 | H65: https://roundlab.com/products/camellia-deep-collagen-jelly-mask-cleanser
A66: Camellia Deep Collagen Lifting Gua Sha Cream | C66: 23 | E66: Sim | G66: RS14W0003 | H66: https://roundlab.com/products/camellia-deep-collagen-lifting-gua-sha-cream
A67: Camellia Deep Collagen Milky PDRN Toner 150ml | C67: 29 | E67: Sim | G67: RS14W0001 | H67: https://roundlab.com/products/camellia-deep-collagen-milky-pdrn-toner-150ml
A68: Camellia Deep Collagen V Lifting Gel Mask | B68: 1 PC | C68: 5.99 | E68: Sim | G68: RM14W0001 | H68: https://roundlab.com/products/camellia-deep-collagen-v-lifting-gel-mask?variant=47349673328854
A69: Camellia Deep Collagen V Lifting Gel Mask | B69: 14PC | C69: 42.99 | E69: Esgotado | G69: RM14W0003 | H69: https://roundlab.com/products/camellia-deep-collagen-v-lifting-gel-mask?variant=47056525787350
A70: Camellia Deep Collagen V Lifting Gel Mask | B70: 4PC | C70: 20.99 | E70: Sim | G70: RM14W0002 | H70: https://roundlab.com/products/camellia-deep-collagen-v-lifting-gel-mask?variant=47056525820118
A71: Daily Hydration Essentials Sheet Mask Bundle (50pcs) | B71: 10 PC Soybean Nourishing Sheet Mask + 10 PC 1025 Dokdo Water Gel Mask Sheet + 10 PC Birch Moisturizing Sheet Mask + 10 PC Pine Calming Cica Sheet Mask + 10 pc Birch Moisturizing Double Gel Mask | C71: 138 | D71: 184 | E71: Esgotado | F71: Sim | G71: a20521e0-bf0e-4ae1-b9f0-3d483745fcc7 | H71: https://roundlab.com/products/bundle-daily-mask-bundle-bulk
A72: Dokdo Cleanser Double Bundle | C72: 28 | D72: 34 | E72: Sim | F72: Sim | G72: RL1025DCLBUNDLE | H72: https://roundlab.com/products/dokdo-cleanser-double-1
A73: Dokdo Cleansing Water | C73: 22.4 | D73: 28 | E73: Sim | G73: RL1025DCW | H73: https://roundlab.com/products/dokdo-cleansing-water
A74: Dokdo Double Cleansing Bundle | C74: 39 | D74: 45 | E74: Sim | F74: Sim | G74: DOKDOCLOIL | H74: https://roundlab.com/products/dokdo-cleanser-dokdo-cleansing-oil-bundle-gift
A75: Dokdo Skin Barrier Hydration Routine Bundle | B75: 200ml 1025 Dokdo Toner + 1025 Dokdo Lotion + 1025 Dokdo Cream + 1025 Dokdo Cleanser + 1025 Dokdo Ampoule + 1 PC 1025 Dokdo Water Gel Mask Sheet | C75: 107 | D75: 127 | E75: Sim | F75: Sim | G75: c15d3c98-f451-479f-b4e3-5693e838a94c | H75: https://roundlab.com/products/dokdo-skin-barrier-hydration-routine
A76: Hydration & Suncare Essentials Trio | C76: 66.29 | D76: 77.99 | E76: Sim | F76: Sim | G76: a5342e9f-5815-4272-b3fa-c21143e6c8ef | H76: https://roundlab.com/products/suncare-trio
A77: Mugwort Calming Cleanser | C77: 17 | E77: Sim | G77: RLMCL150 | H77: https://roundlab.com/products/mugwort-calming-cleanser
A78: Mugwort Calming Cream | C78: 36 | E78: Sim | G78: RLMCC300 | H78: https://roundlab.com/products/mugwort-calming-cream
A79: Mugwort Calming Routine Bundle | C79: 86.25 | D79: 115 | E79: Sim | F79: Sim | G79: f52ab8b9-8617-44f1-b8ce-5b233a78069f | H79: https://roundlab.com/products/mugwort-routine-bundle
A80: Mugwort Calming Serum | C80: 31 | E80: Sim | G80: RLMCS50 | H80: https://roundlab.com/products/mugwort-calming-serum
A81: Mugwort Calming Sheet Mask | B81: 1 PC | C81: 4 | E81: Sim | G81: RLMCSM1 | H81: https://roundlab.com/products/mugwort-calming-sheet-mask?variant=43610238386390
A82: Mugwort Calming Sheet Mask | B82: 10 PC | C82: 36 | E82: Sim | G82: RLMCSM3 | H82: https://roundlab.com/products/mugwort-calming-sheet-mask?variant=43734089793750
A83: Mugwort Calming Sheet Mask | B83: 5 PC | C83: 19 | E83: Sim | G83: RLMCSM2 | H83: https://roundlab.com/products/mugwort-calming-sheet-mask?variant=43610238419158
A84: Mugwort Calming Toner | C84: 27 | E84: Sim | G84: RLMCT300 | H84: https://roundlab.com/products/mugwort-calming-toner
A85: Nourishing Soybean Hydration Routine Bundle | C85: 98.7 | D85: 141 | E85: Sim | F85: Sim | G85: 935fef0d-9bd2-42f1-8335-24f56d4f4cb9 | H85: https://roundlab.com/products/spilling-the-beans-winter-hydration-bundle
A86: Pine Calming Cica Ampoule | C86: 25 | E86: Sim | G86: RLPCA30 | H86: https://roundlab.com/products/pine-tree-cica-care-ampoule
A87: Pine Calming Cica Body Wash | C87: 24 | E87: Sim | G87: RLPCBDWH | H87: https://roundlab.com/products/pine-cica-calming-body-wash
A88: Pine Calming Cica Body and Scalp Care Bundle | C88: 61.2 | D88: 68 | E88: Sim | F88: Sim | H88: https://roundlab.com/products/pine-calming-cica-body-and-scalp-care-bundle-1
A89: Pine Calming Cica Cleanser | C89: 17 | E89: Sim | G89: RLPCCLSR | H89: https://roundlab.com/products/pine-calming-cica-cleanser
A90: Pine Calming Cica Cream | C90: 31 | E90: Sim | G90: RLPCC50 | H90: https://roundlab.com/products/pine-tree-cica-cream
A91: Pine Calming Cica Lotion | C91: 28 | E91: Sim | G91: RLPCCL | H91: https://roundlab.com/products/pine-calming-cica-lotion
A92: Pine Calming Cica Primer Sunscreen 50ml | C92: 24.99 | E92: Sim | G92: RU03G0002 | H92: https://roundlab.com/products/pine-calming-cica-primer-sunscreen-50ml
A93: Pine Calming Cica Shampoo | C93: 22 | E93: Sim | G93: RB03G0004 | H93: https://roundlab.com/products/pine-calming-cica-shampoo
A94: Pine Calming Cica Sheet Mask | B94: 1 PC | C94: 4 | E94: Sim | G94: RLPCSM27 | H94: https://roundlab.com/products/pine-tree-cica-sheet-mask?variant=44067264561366
A95: Pine Calming Cica Sheet Mask | B95: 10 PC | C95: 36 | E95: Sim | G95: RLPCSM29 | H95: https://roundlab.com/products/pine-tree-cica-sheet-mask?variant=43734092054742
A96: Pine Calming Cica Sheet Mask | B96: 5 PC | C96: 19 | E96: Sim | G96: RLPCSM28 | H96: https://roundlab.com/products/pine-tree-cica-sheet-mask?variant=43610245103830
A97: Pine Calming Cica Toner | C97: 25 | E97: Sim | G97: RLPCT250 | H97: https://roundlab.com/products/pine-calming-cica-toner
A98: Pine Calming Cica Toner Pad | C98: 28 | E98: Sim | G98: RLPCP50 | H98: https://roundlab.com/products/pine-tree-cica-pad
A99: Pine Cica Calming Nose Deep Cleansing Mask Kit (5 pack) | C99: 18 | E99: Sim | F99: Sim | G99: RM03G0011 | H99: https://roundlab.com/products/pine-cica-calming-nose-deep-cleansing-mask-5-pc
A100: Pine Cica Calming Routine Bundle | C100: 96.9 | D100: 102 | E100: Sim | F100: Sim | G100: 59b520f7-3ee3-4a41-8003-b4260bedb776 | H100: https://roundlab.com/products/pine-cica-calming-routine
...

Sheet Parâmetros
A1: Câmbio US$ → R$ | B1: 5.4
A2: Acréscimo sobre o preço do exterior | B2: 0.2
A4: Mude os valores acima e a coluna "Mercadoria sugerida" recalcula.
A5: Site oficial: https://roundlab.com · loja "Round Lab" · moeda USD · lido em 30/10/2026 06:07 UTC
A6: Regra (Guia de precificação OMG): produto sem concorrente válido → varejo no exterior em US$ + 20%, convertido = preço da mercadoria no site. Frete e impostos entram no checkout.
